dbbasic_deploy/__init__.py
dbbasic_deploy/cli.py
dbbasic_deploy/deploy.py
dbbasic_deploy/setup.py
dbbasic_deploy-0.1.0.dist-info/METADATA
dbbasic_deploy-0.1.0.dist-info/WHEEL
dbbasic_deploy-0.1.0.dist-info/entry_points.txt
dbbasic_deploy-0.1.0.dist-info/top_level.txt
dbbasic_deploy-0.1.0.dist-info/RECORD
