Metadata-Version: 2.4
Name: dbbasic-deploy
Version: 0.1.0
Summary: Simple SSH deployment tool for dbbasic-web apps to Ubuntu servers
Author-email: DBBasic <noreply@dbbasic.com>
License: MIT
Project-URL: Homepage, https://github.com/askrobots/dbbasic-deploy
Project-URL: Repository, https://github.com/askrobots/dbbasic-deploy
Keywords: deployment,ssh,web,ubuntu,nginx,systemd
Classifier: Development Status :: 3 - Alpha
Classifier: Intended Audience :: Developers
Classifier: Topic :: Software Development :: Build Tools
Classifier: Topic :: System :: Systems Administration
Classifier: License :: OSI Approved :: MIT License
Classifier: Programming Language :: Python :: 3
Classifier: Programming Language :: Python :: 3.10
Classifier: Programming Language :: Python :: 3.11
Classifier: Programming Language :: Python :: 3.12
Classifier: Operating System :: OS Independent
Requires-Python: >=3.10
Requires-Dist: paramiko>=3.0.0
Requires-Dist: click>=8.0.0
